sphinxcontrib_wavedrom-3.0.4-py3.8-nspkg.pth
sphinxcontrib/version.py
sphinxcontrib/wavedrom.py
sphinxcontrib/wavedrom_render_image.py
sphinxcontrib_wavedrom-3.0.4.dist-info/LICENSE.txt
sphinxcontrib_wavedrom-3.0.4.dist-info/METADATA
sphinxcontrib_wavedrom-3.0.4.dist-info/WHEEL
sphinxcontrib_wavedrom-3.0.4.dist-info/namespace_packages.txt
sphinxcontrib_wavedrom-3.0.4.dist-info/top_level.txt
sphinxcontrib_wavedrom-3.0.4.dist-info/RECORD
