Metadata-Version: 2.1
Name: sphinxcontrib-wavedrom
Version: 3.0.4
Summary: A sphinx extension that allows generating wavedrom diagrams based on their textual representation
Home-page: https://github.com/bavovanachte/sphinx-wavedrom
Author: Bavo Van Achte, Stefan Wallentowitz
Author-email: bavo.van.achte@gmail.com, stefan@wallentowitz.de
License: MIT license
Keywords: sphinx,wavedrom,documentation
Platform: any
Requires-Dist: Sphinx (>=1.8)
Requires-Dist: wavedrom (>=1.9.0rc1)
Requires-Dist: cairosvg (>=2) ; python_version >= "3.3"
Requires-Dist: xcffib ; python_version >= "3.3"
